LICENSE.txt
MANIFEST.in
README.rst
setup.py
bin/jp
jmespathv041p/__init__.py
jmespathv041p/ast.py
jmespathv041p/compat.py
jmespathv041p/exceptions.py
jmespathv041p/lexer.py
jmespathv041p/parser.py
jmespathv041p.egg-info/PKG-INFO
jmespathv041p.egg-info/SOURCES.txt
jmespathv041p.egg-info/dependency_links.txt
jmespathv041p.egg-info/top_level.txt