Metadata-Version: 1.1
Name: jmespathv041p
Version: 0.4.1
Summary: JSON Matching Expressions
Home-page: https://github.com/henrysher/jmespathv041p
Author: James Saryerwinnie
Author-email: js@jamesls.com
License: UNKNOWN
Platform: UNKNOWN
Classifier: Development Status :: 5 - Production/Stable
Classifier: Intended Audience :: Developers
Classifier: Natural Language :: English
Classifier: License :: OSI Approved :: MIT License
Classifier: Programming Language :: Python
Classifier: Programming Language :: Python :: 2.6
Classifier: Programming Language :: Python :: 2.7
Classifier: Programming Language :: Python :: 3
Classifier: Programming Language :: Python :: 3.3
